glance_store/__init__.py
glance_store/backend.py
glance_store/capabilities.py
glance_store/driver.py
glance_store/exceptions.py
glance_store/i18n.py
glance_store/location.py
glance_store/multi_backend.py
glance_store/_drivers/__init__.py
glance_store/_drivers/filesystem.py
glance_store/_drivers/http.py
glance_store/_drivers/rbd.py
glance_store/_drivers/s3.py
glance_store/_drivers/vmware_datastore.py
glance_store/_drivers/cinder/__init__.py
glance_store/_drivers/cinder/base.py
glance_store/_drivers/cinder/nfs.py
glance_store/_drivers/cinder/scaleio.py
glance_store/_drivers/cinder/store.py
glance_store/_drivers/swift/__init__.py
glance_store/_drivers/swift/buffered.py
glance_store/_drivers/swift/connection_manager.py
glance_store/_drivers/swift/store.py
glance_store/_drivers/swift/utils.py
glance_store/common/__init__.py
glance_store/common/attachment_state_manager.py
glance_store/common/cinder_utils.py
glance_store/common/fs_mount.py
glance_store/common/utils.py
glance_store/locale/en_GB/LC_MESSAGES/glance_store.po
glance_store/locale/ko_KR/LC_MESSAGES/glance_store.po
glance_store/tests/__init__.py
glance_store/tests/base.py
glance_store/tests/fakes.py
glance_store/tests/utils.py
glance_store/tests/etc/glance-swift.conf
glance_store/tests/functional/README.rst
glance_store/tests/functional/__init__.py
glance_store/tests/functional/base.py
glance_store/tests/functional/filesystem/__init__.py
glance_store/tests/functional/filesystem/test_functional_filesystem.py
glance_store/tests/functional/swift/__init__.py
glance_store/tests/functional/swift/test_functional_swift.py
glance_store/tests/unit/__init__.py
glance_store/tests/unit/test_backend.py
glance_store/tests/unit/test_backend_group_configuration.py
glance_store/tests/unit/test_connection_manager.py
glance_store/tests/unit/test_driver.py
glance_store/tests/unit/test_exceptions.py
glance_store/tests/unit/test_filesystem_store.py
glance_store/tests/unit/test_http_store.py
glance_store/tests/unit/test_location.py
glance_store-5.1.0.dist-info/AUTHORS
glance_store-5.1.0.dist-info/LICENSE
glance_store-5.1.0.dist-info/METADATA
glance_store-5.1.0.dist-info/WHEEL
glance_store-5.1.0.dist-info/entry_points.txt
glance_store-5.1.0.dist-info/pbr.json
glance_store-5.1.0.dist-info/top_level.txt
glance_store-5.1.0.dist-info/RECORD
